{
  "editor.formatOnSave": true,
  "python.linting.enabled": true,
  "python.linting.pylintEnabled": false,
  "python.linting.mypyEnabled": true,
  "python.linting.flake8Enabled": true,
  "python.linting.mypyArgs": ["--strict"],
  "python.formatting.provider": "black",
  "files.insertFinalNewline": true,
  "editor.defaultFormatter": "esbenp.prettier-vscode",
  "[python]": {
    "editor.defaultFormatter": "ms-python.python"
  },
  "python.defaultInterpreterPath": "",
  "python.testing.pytestArgs": ["tests"],
  "python.testing.unittestEnabled": false,
  "python.testing.pytestEnabled": true
}
